telegram_news/__init__.py
telegram_news/constant.py
telegram_news/displaypolicy.py
telegram_news/ratelimit.py
telegram_news/table.sql
telegram_news/utils.py
telegram_news/template/__init__.py
telegram_news/template/common.py
telegramweb-6.16.dist-info/LICENSE
telegramweb-6.16.dist-info/METADATA
telegramweb-6.16.dist-info/WHEEL
telegramweb-6.16.dist-info/top_level.txt
telegramweb-6.16.dist-info/RECORD
