Metadata-Version: 2.1
Name: telegramweb
Version: 6.16
Summary: Python package for automatically fetching and pushing news by Telegram.
Home-page: https://github.com/craziks-creator/telegram-web
Author: craziks
Author-email: chandrashekharpanday07@gmail.com
License: MIT
Platform: UNKNOWN
Classifier: Development Status :: 3 - Alpha
Classifier: License :: OSI Approved :: MIT License
Classifier: Operating System :: OS Independent
Classifier: Programming Language :: Python :: 3.9
Classifier: Programming Language :: Python :: 3.10
Classifier: Programming Language :: Python :: 3.11
Classifier: Programming Language :: Python :: 3.8
Classifier: Intended Audience :: Developers
Classifier: Topic :: Education
Classifier: Topic :: Office/Business :: News/Diary
Classifier: Topic :: Software Development :: Libraries :: Python Modules
Requires-Python: >=3.8
License-File: LICENSE
Requires-Dist: requests
Requires-Dist: SQLAlchemy
Requires-Dist: beautifulsoup4
Requires-Dist: psycopg2-binary
Requires-Dist: lxml
Requires-Dist: xmltodict
